odoo/addons/sale_automatic_workflow_stock/README.rst
odoo/addons/sale_automatic_workflow_stock/__init__.py
odoo/addons/sale_automatic_workflow_stock/__manifest__.py
odoo/addons/sale_automatic_workflow_stock/data/automatic_workflow_data.xml
odoo/addons/sale_automatic_workflow_stock/i18n/it.po
odoo/addons/sale_automatic_workflow_stock/i18n/sale_automatic_workflow_stock.pot
odoo/addons/sale_automatic_workflow_stock/models/__init__.py
odoo/addons/sale_automatic_workflow_stock/models/automatic_workflow_job.py
odoo/addons/sale_automatic_workflow_stock/models/sale_order.py
odoo/addons/sale_automatic_workflow_stock/models/sale_workflow_process.py
odoo/addons/sale_automatic_workflow_stock/models/stock_move.py
odoo/addons/sale_automatic_workflow_stock/models/stock_picking.py
odoo/addons/sale_automatic_workflow_stock/readme/CONTRIBUTORS.md
odoo/addons/sale_automatic_workflow_stock/readme/CREDITS.md
odoo/addons/sale_automatic_workflow_stock/readme/DESCRIPTION.md
odoo/addons/sale_automatic_workflow_stock/static/description/icon.png
odoo/addons/sale_automatic_workflow_stock/static/description/index.html
odoo/addons/sale_automatic_workflow_stock/tests/__init__.py
odoo/addons/sale_automatic_workflow_stock/tests/common.py
odoo/addons/sale_automatic_workflow_stock/tests/test_automatic_workflow.py
odoo/addons/sale_automatic_workflow_stock/tests/test_multicompany.py
odoo/addons/sale_automatic_workflow_stock/views/sale_order_views.xml
odoo/addons/sale_automatic_workflow_stock/views/sale_workflow_process_views.xml
odoo_addon_sale_automatic_workflow_stock-18.0.1.0.0.2.dist-info/METADATA
odoo_addon_sale_automatic_workflow_stock-18.0.1.0.0.2.dist-info/WHEEL
odoo_addon_sale_automatic_workflow_stock-18.0.1.0.0.2.dist-info/top_level.txt
odoo_addon_sale_automatic_workflow_stock-18.0.1.0.0.2.dist-info/RECORD
